django_tastypie-0.14.0.dist-info/DESCRIPTION.rst
django_tastypie-0.14.0.dist-info/METADATA
django_tastypie-0.14.0.dist-info/metadata.json
django_tastypie-0.14.0.dist-info/RECORD
django_tastypie-0.14.0.dist-info/top_level.txt
django_tastypie-0.14.0.dist-info/WHEEL
tastypie/__init__.py
tastypie/admin.py
tastypie/api.py
tastypie/authentication.py
tastypie/authorization.py
tastypie/bundle.py
tastypie/cache.py
tastypie/compat.py
tastypie/constants.py
tastypie/exceptions.py
tastypie/fields.py
tastypie/http.py
tastypie/models.py
tastypie/paginator.py
tastypie/resources.py
tastypie/serializers.py
tastypie/test.py
tastypie/throttle.py
tastypie/validation.py
tastypie/contrib/__init__.py
tastypie/contrib/contenttypes/__init__.py
tastypie/contrib/contenttypes/fields.py
tastypie/contrib/contenttypes/resources.py
tastypie/contrib/gis/__init__.py
tastypie/contrib/gis/resources.py
tastypie/management/__init__.py
tastypie/management/commands/__init__.py
tastypie/management/commands/backfill_api_keys.py
tastypie/migrations/0001_initial.py
tastypie/migrations/__init__.py
tastypie/templates/tastypie/basic.html
tastypie/templates/tastypie/detail.html
tastypie/templates/tastypie/list.html
tastypie/utils/__init__.py
tastypie/utils/dict.py
tastypie/utils/formatting.py
tastypie/utils/mime.py
tastypie/utils/timezone.py
tastypie/utils/urls.py
tastypie/utils/validate_jsonp.py
