Metadata-Version: 1.1
Name: django-tastypie
Version: 0.14.0
Summary: A flexible & capable API layer for Django.
Home-page: https://github.com/django-tastypie/django-tastypie
Author: Daniel Lindsley
Author-email: daniel@toastdriven.com
License: UNKNOWN
Platform: UNKNOWN
Classifier: Development Status :: 4 - Beta
Classifier: Environment :: Web Environment
Classifier: Framework :: Django
Classifier: Intended Audience :: Developers
Classifier: License :: OSI Approved :: BSD License
Classifier: Operating System :: OS Independent
Classifier: Programming Language :: Python
Classifier: Programming Language :: Python :: 2
Classifier: Programming Language :: Python :: 3
Classifier: Topic :: Utilities
Requires: python_mimeparse(>=0.1.4, !=1.5)
Requires: dateutil(>=1.5, !=2.0)
